tartiflette_django/__init__.py
tartiflette_django/apps.py
tartiflette_django/checks.py
tartiflette_django/engine.py
tartiflette_django/resolvers.py
tartiflette_django/settings.py
tartiflette_django/utils.py
tartiflette_django/views.py
tartiflette_django/templates/tartiflette/graphiql.html
tartiflette_django-0.1.1.dist-info/METADATA
tartiflette_django-0.1.1.dist-info/WHEEL
tartiflette_django-0.1.1.dist-info/top_level.txt
tartiflette_django-0.1.1.dist-info/RECORD
